g3tester/__init__.py
g3tester/_memory.py
g3tester/_test.py
g3tester/enums.py
g3tester/exceptions.py
g3tester/py.typed
g3tester/tags/__init__.py
g3tester/tags/_tags.py
g3tester/testinfo/__init__.py
g3tester/testinfo/_testinfo.py
g3tester/testlib/__init__.py
g3tester/testlib/all/__init__.py
g3tester/testlib/detector/__init__.py
g3tester/testlib/detector/_detector.py
g3tester/testlib/element/__init__.py
g3tester/testlib/element/_element.py
g3tester/testlib/pointmachine/__init__.py
g3tester/testlib/pointmachine/_pointmachine.py
g3tester/testlib/route/__init__.py
g3tester/testlib/route/_passage_generator.py
g3tester/testlib/route/_route.py
g3tester/testlib/zone/__init__.py
g3tester/testlib/zone/_zone.py
g3tester-0.1.1.dist-info/LICENCE
g3tester-0.1.1.dist-info/METADATA
g3tester-0.1.1.dist-info/WHEEL
g3tester-0.1.1.dist-info/top_level.txt
g3tester-0.1.1.dist-info/RECORD
